setup.py
gaussian_binomial_dist_package/Binomialdistribution.py
gaussian_binomial_dist_package/Gaussiandistribution.py
gaussian_binomial_dist_package/Generaldistribution.py
gaussian_binomial_dist_package/__init__.py
gaussian_binomial_dist_package.egg-info/PKG-INFO
gaussian_binomial_dist_package.egg-info/SOURCES.txt
gaussian_binomial_dist_package.egg-info/dependency_links.txt
gaussian_binomial_dist_package.egg-info/not-zip-safe
gaussian_binomial_dist_package.egg-info/top_level.txt