Metadata-Version: 1.0
Name: gaussian-binomial-dist-package
Version: 0.1
Summary: Gaussian and Binomial distributions
Home-page: UNKNOWN
Author: Samuel K
Author-email: samuelkabelo1@gmail.com
License: UNKNOWN
Platform: UNKNOWN
